{
  "type": "workspace",
  "questions": [
    {
      "name": "Eason",
      "message": "Enter author full name",
      "defaultFrom": "git.user.name",
      "required": true
    },
    {
      "name": "sdqede@gmail.com",
      "message": "Enter author email",
      "defaultFrom": "git.user.email",
      "required": true
    },
    {
      "name": "repo1",
      "message": "Enter the repository name",
      "required": true
    },
    {
      "name": "sdqede",
      "message": "Enter your github username",
      "defaultFrom": "npm.whoami",
      "required": true
    },
    {
      "name": "Apache-2.0",
      "message": "Choose a license",
      "type": "list",
      "options": [
        "MIT",
        "Apache-2.0",
        "ISC",
        "BSD-3-Clause",
        "GPL-3.0",
        "MPL-2.0",
        "Unlicense"
      ],
      "required": true
    }
  ]
}

